odoo9_addon_account_asset_depr_line_cancel-9.0.1.0.0.99.dev5-py2.7-nspkg.pth
odoo9_addon_account_asset_depr_line_cancel-9.0.1.0.0.99.dev5.dist-info/DESCRIPTION.rst
odoo9_addon_account_asset_depr_line_cancel-9.0.1.0.0.99.dev5.dist-info/METADATA
odoo9_addon_account_asset_depr_line_cancel-9.0.1.0.0.99.dev5.dist-info/RECORD
odoo9_addon_account_asset_depr_line_cancel-9.0.1.0.0.99.dev5.dist-info/WHEEL
odoo9_addon_account_asset_depr_line_cancel-9.0.1.0.0.99.dev5.dist-info/metadata.json
odoo9_addon_account_asset_depr_line_cancel-9.0.1.0.0.99.dev5.dist-info/namespace_packages.txt
odoo9_addon_account_asset_depr_line_cancel-9.0.1.0.0.99.dev5.dist-info/top_level.txt
odoo_addons/account_asset_depr_line_cancel/README.rst
odoo_addons/account_asset_depr_line_cancel/__init__.py
odoo_addons/account_asset_depr_line_cancel/__openerp__.py
odoo_addons/account_asset_depr_line_cancel/i18n/account_asset_depr_line_cancel.pot
odoo_addons/account_asset_depr_line_cancel/i18n/ar.po
odoo_addons/account_asset_depr_line_cancel/i18n/bs.po
odoo_addons/account_asset_depr_line_cancel/i18n/cs.po
odoo_addons/account_asset_depr_line_cancel/i18n/de.po
odoo_addons/account_asset_depr_line_cancel/i18n/en_GB.po
odoo_addons/account_asset_depr_line_cancel/i18n/es.po
odoo_addons/account_asset_depr_line_cancel/i18n/es_CR.po
odoo_addons/account_asset_depr_line_cancel/i18n/es_EC.po
odoo_addons/account_asset_depr_line_cancel/i18n/es_MX.po
odoo_addons/account_asset_depr_line_cancel/i18n/fr.po
odoo_addons/account_asset_depr_line_cancel/i18n/hr.po
odoo_addons/account_asset_depr_line_cancel/i18n/it.po
odoo_addons/account_asset_depr_line_cancel/i18n/ja.po
odoo_addons/account_asset_depr_line_cancel/i18n/mk.po
odoo_addons/account_asset_depr_line_cancel/i18n/mn.po
odoo_addons/account_asset_depr_line_cancel/i18n/nb.po
odoo_addons/account_asset_depr_line_cancel/i18n/nl.po
odoo_addons/account_asset_depr_line_cancel/i18n/nl_BE.po
odoo_addons/account_asset_depr_line_cancel/i18n/pt.po
odoo_addons/account_asset_depr_line_cancel/i18n/pt_BR.po
odoo_addons/account_asset_depr_line_cancel/i18n/pt_PT.po
odoo_addons/account_asset_depr_line_cancel/i18n/ro.po
odoo_addons/account_asset_depr_line_cancel/i18n/ru.po
odoo_addons/account_asset_depr_line_cancel/i18n/sl.po
odoo_addons/account_asset_depr_line_cancel/i18n/sv.po
odoo_addons/account_asset_depr_line_cancel/i18n/tr.po
odoo_addons/account_asset_depr_line_cancel/i18n/zh_CN.po
odoo_addons/account_asset_depr_line_cancel/i18n/zh_TW.po
odoo_addons/account_asset_depr_line_cancel/models/__init__.py
