Metadata-Version: 2.0
Name: odoo9-addon-account-asset-depr-line-cancel
Version: 9.0.1.0.0.99.dev5
Summary: Assets Management - Cancel button
Home-page: http://www.serviciosbaeza.com
Author: Tecnativa, Odoo Community Association (OCA)
Author-email: support@odoo-community.org
License: AGPL-3
Platform: UNKNOWN
Classifier: Programming Language :: Python
Classifier: Framework :: Odoo
Classifier: License :: OSI Approved :: GNU Affero General Public License v3
Requires-Python: ~=2.7
Requires-Dist: odoo (<9.1a,>=9.0a)
